sphinx_plausible/__init__.py
sphinx_plausible/_version.py
sphinx_plausible-0.1.2.dist-info/LICENSE
sphinx_plausible-0.1.2.dist-info/WHEEL
sphinx_plausible-0.1.2.dist-info/METADATA
sphinx_plausible-0.1.2.dist-info/RECORD
