Metadata-Version: 2.1
Name: sphinx-plausible
Version: 0.1.2
Summary: Sphinx extension for plausible.io analytics
Author: Richard Darst
Requires-Python: >=3
Classifier: Programming Language :: Python :: 3
Classifier: License :: OSI Approved :: MIT License
Classifier: Framework :: Sphinx
Classifier: Framework :: Sphinx :: Extension
Requires-Dist: sphinx>1.8
Requires-Dist: sphinx>1.8 ; extra == "test"
Project-URL: Home, https://github.com/rkdarst/sphinx-plausible/
Provides-Extra: test
